{
  "2026-07-07": {
    "picks": [
      {
        "code": "3711",
        "name": "日月光投控",
        "score": 4
      },
      {
        "code": "2379",
        "name": "瑞昱",
        "score": 4
      },
      {
        "code": "2890",
        "name": "永豐金",
        "score": 4
      },
      {
        "code": "2892",
        "name": "第一金",
        "score": 4
      },
      {
        "code": "2408",
        "name": "南亞科",
        "score": 4
      },
      {
        "code": "2327",
        "name": "國巨",
        "score": 4
      },
      {
        "code": "2330",
        "name": "台積電",
        "score": 3
      },
      {
        "code": "1216",
        "name": "統一",
        "score": 3
      },
      {
        "code": "2886",
        "name": "兆豐金",
        "score": 3
      },
      {
        "code": "2885",
        "name": "元大金",
        "score": 3
      },
      {
        "code": "2603",
        "name": "長榮",
        "score": 3
      },
      {
        "code": "4967",
        "name": "十銓",
        "score": 3
      },
      {
        "code": "2887",
        "name": "台新金",
        "score": 3
      },
      {
        "code": "2454",
        "name": "聯發科",
        "score": 2
      },
      {
        "code": "2303",
        "name": "聯電",
        "score": 2
      }
    ]
  }
}